assembly_client/__init__.py
assembly_client/api.py
assembly_client/cli.py
assembly_client/errors.py
assembly_client/parser.py
assembly_client/sync.py
assembly_client/codegen/generator.py
assembly_client/generated/__init__.py
assembly_client/generated/models.py
assembly_client/generated/services.py
assembly_api_client-1.2.1.dist-info/METADATA
assembly_api_client-1.2.1.dist-info/WHEEL
assembly_api_client-1.2.1.dist-info/RECORD
