Metadata-Version: 2.4
Name: assembly-api-client
Version: 1.2.1
Summary: A Python client for the Korean National Assembly Open API
Author-email: StatPan <statpan@naver.com>
License: MIT
Classifier: Development Status :: 5 - Production/Stable
Classifier: Intended Audience :: Developers
Classifier: License :: OSI Approved :: MIT License
Classifier: Programming Language :: Python :: 3
Requires-Python: >=3.8
Requires-Dist: httpx>=0.24.0
Requires-Dist: openpyxl>=3.1.0
Requires-Dist: platformdirs>=3.0.0
Requires-Dist: pydantic>=2.0.0
Requires-Dist: python-dotenv>=1.0.0
Requires-Dist: rich>=13.0.0
Requires-Dist: tenacity>=8.0.0
Requires-Dist: typer>=0.9.0
